Metadata-Version: 2.1
Name: multiprocess-chunks
Version: 1.0.0
Summary: Chunk-based, multiprocess processing of iterables.
Home-page: https://github.com/malcolmvr/multiprocess-chunks
Author: Malcolm van Raalte
Author-email: malcolm@van.raalte.ca
License: MIT
Download-URL: https://github.com/malcolmvr/multiprocess-chunks/archive/v1.0.0.tar.gz
Keywords: multiprocess,multiprocessing,pickle,pickling,chunks,map
Platform: UNKNOWN
Classifier: Development Status :: 5 - Production/Stable
Classifier: Topic :: Software Development :: Build Tools
Classifier: License :: OSI Approved :: MIT License
Classifier: Programming Language :: Python :: 3.3
Classifier: Programming Language :: Python :: 3.4
Classifier: Programming Language :: Python :: 3.5
Classifier: Programming Language :: Python :: 3.6
Classifier: Programming Language :: Python :: 3.7
Classifier: Programming Language :: Python :: 3.8
Requires-Python: >=3.3
